LICENSE
MANIFEST.in
README.md
setup.py
version
youtrack/__init__.py
youtrack/connection.py
youtrack/importHelper.py
youtrack/youtrackImporter.py
youtrack.egg-info/PKG-INFO
youtrack.egg-info/SOURCES.txt
youtrack.egg-info/dependency_links.txt
youtrack.egg-info/requires.txt
youtrack.egg-info/top_level.txt
youtrack/sync/__init__.py
youtrack/sync/comments.py
youtrack/sync/executing.py
youtrack/sync/fields.py
youtrack/sync/issues.py
youtrack/sync/links.py
youtrack/sync/logging.py
youtrack/sync/roles.py
youtrack/sync/states.py
youtrack/sync/users.py
youtrack/sync/youtracks.py