Metadata-Version: 2.1
Name: youtrack
Version: 0.1.52
Summary: Python library for interacting with YouTrack via REST API supporting python3
Home-page: https://github.com/JetBrains/youtrack-rest-python-library
Maintainer: Alexander Buturlinov
Maintainer-email: imboot85@gmail.com
License: Apache 2.0
Platform: UNKNOWN
Classifier: Programming Language :: Python :: 3
Classifier: License :: OSI Approved :: Apache Software License
Classifier: Operating System :: OS Independent
Requires-Python: >3
